{
  "scripts": {
    "start": "yarn workspace @ulixee/cloud start",
    "test:build": "cross-env NODE_ENV=test ULX_DATA_DIR=.data-test jest"
  },
  "devDependencies": {
    "jest": "^28.1.0",
    "jest-environment-node": "^28.1.0",
    "jest-summary-reporter": "^0.0.2",
    "cross-env": "^7.0.3"
  },
  "workspaces": {
    "packages": [
      "desktop/main",
      "desktop/core",
      "desktop/interfaces",
      "datastore/*",
      "datastore/plugins/*",
      "cloud/*",
      "sql/*",
      "client/*",
      "cli",
      "specification",
      "end-to-end",
      "playgrounds/*",
      "hero/build/*",
      "hero/build/plugins/*",
      "../shared/build/*",
      "../payments/build/sidechain/client",
      "../unblocked/build/agent/*",
      "../unblocked/build/plugins/*",
      "../unblocked/build/specification",
      "../unblocked/build/js-path",
      "../unblocked/build/real-user-agents"
    ],
    "nohoist": [
      "**/babel-loader",
      "**/electron-webpack",
      "**/@electron",
      "**/@electron/**",
      "**/electron",
      "**/electron-*",
      "**/electron-builder",
      "**/electron-webpack/**",
      "**/nseventmonitor",
      "**/global-mouse-events",
      "**/electron-clipboard-ex",
      "**/@ulixee/repo-tools",
      "**/@vue/**",
      "**/@vue/**/**",
      "**/vue",
      "**/vue-loader",
      "**/vue-template-compiler",
      "**/vue-class-component",
      "**/@types/web",
      "**/autoprefixer",
      "**/postcss",
      "**/tailwindcss",
      "**/@nodelib",
      "**/@nodelib/**"
    ]
  }
}
